pythonprojectstructure/__init__.py
pythonprojectstructure/__main__.py
pythonprojectstructure/utils.py
pythonprojectstructure/version.py
pythonprojectstructure/tests/__init__.py
pythonprojectstructure/tests/test_cli.py
python_project_structure-0.8.25.dist-info/LICENSE
python_project_structure-0.8.25.dist-info/METADATA
python_project_structure-0.8.25.dist-info/WHEEL
python_project_structure-0.8.25.dist-info/entry_points.txt
python_project_structure-0.8.25.dist-info/top_level.txt
python_project_structure-0.8.25.dist-info/RECORD
