Metadata-Version: 2.1
Name: python-project-structure
Version: 0.8.25
Summary: Python project structure foundation or template, CLI console scripts.
Home-page: https://gitlab.com/rpatterson/python-project-structure
Author: Ross Patterson
Author-email: me@rpatterson.net
License: MIT
Keywords: template,structure
Classifier: Development Status :: 4 - Beta
Classifier: Environment :: Console
Classifier: Intended Audience :: Developers
Classifier: Intended Audience :: System Administrators
Classifier: License :: OSI Approved :: MIT License
Classifier: Natural Language :: English
Classifier: Operating System :: OS Independent
Classifier: Programming Language :: Python :: 3
Classifier: Programming Language :: Python :: 3.11
Classifier: Programming Language :: Python :: 3.10
Classifier: Programming Language :: Python :: 3.9
Classifier: Programming Language :: Python :: 3.8
Classifier: Programming Language :: Python :: 3.7
Classifier: Topic :: Utilities
Requires-Python: >=3.7
License-File: LICENSE
Requires-Dist: argcomplete
Provides-Extra: devel
Requires-Dist: pytest ; extra == 'devel'
Requires-Dist: coverage ; extra == 'devel'
Requires-Dist: prospector[with_everything] ; extra == 'devel'
Requires-Dist: xenon ; extra == 'devel'
Requires-Dist: rstcheck ; extra == 'devel'
Requires-Dist: black ; extra == 'devel'
Requires-Dist: autoflake ; extra == 'devel'
Requires-Dist: autopep8 ; extra == 'devel'
Requires-Dist: pip-tools ; extra == 'devel'
Requires-Dist: towncrier ; extra == 'devel'
Requires-Dist: build ; extra == 'devel'
